# 字节码原理

详细参考：

+ 《深入理解JVM字节码》前３章节，可惜这本书并没有深入说明字节码是怎么解释执行的, 字节码总结也不全不详细
+ [字节码指令表](./字节码指令表.md)



## 字节码原理

+ **字节码的作用**

  字节码是介于源码（如Java源码）和机器码中间的一种抽象表示方法，通过JVM解释器解释执行或通过JIT编译成机器码执行。

+ **字节码的构成**

  ```txt
  //操作码 + 操作数
  <opcode> [<operand1>, <operand2>]
  ```

  字节码操作码由一个字节表示，所以称作字节码。

  字节码采用大端序表示，即高位在前、低位在后。

+ **字节码分类**
  
  参考字节码指令表。
  
+ **字节码的解释执行**

  + Java虚拟机的栈和栈帧

    字节码只是描述操作指令和操作数，但是就像机器码执行需要计算单元和寄存器一样，字节码解释执行的过程也需要有可以存储操作数和存储执行结果的空间，对Java Hotspot虚拟机来说，栈就是这些空间，栈由很多栈帧组成，每个栈帧对应一次方法调用，栈帧包含局部变量表、操作数栈、动态连接、方法返回地址。

    字节码指令的执行都伴随着局部变量表和操作数栈的不断加载和存储的过程。

    比如：

    ```java
    //Java源码
    int i = 0;
    synchronized(lock) {
    	++i;
    }
    System.out.println(i);
    
    //对应的字节码（这里的栈都是指操作树栈）
    0: iconst_0      			//将int类型的值０压入操作数栈栈顶
    1: istore_1      			//栈顶的值存储到局部变量表下标为１的位置（注意下标为０的位置存的是this）
    //synchronized块开始
    2: getstatic     #2                  // Field lock:Ljava/lang/Object;	//获取#2的对象引用将值压入栈顶
    5: dup           			//复制栈顶数据（此时是lock对象引用）并入栈
    6: astore_2      			//栈顶的引用类型的值存储到局部变量表下标为２的位置
    7: monitorenter  			//获取对象的monitor
    8: iinc          1, 1
    11: aload_2       			//把局部变量表第2个引用型局部变量压入栈顶
    12: monitorexit   			//释放对象的monitor
    //synchronized块结束
    13: goto          21
    16: astore_3      
    17: aload_2       
    18: monitorexit   
    19: aload_3       
    20: athrow        
    
    ```

21: getstatic     #3                  // Field java/lang/System.out:Ljava/io/PrintStream;
    24: iload_1       
25: invokevirtual #4                  // Method java/io/PrintStream.println:(I)V
    28: return 
```
    
    > 虚拟机分为基于栈实现和基于寄存器实现，Hotspot是基于栈实现的。
  
  + 解释执行
  
    TODO
```